{
  "logoType": "none",
  "logo": {
    "lucideIcon": "",
    "imagePath": "",
    "imageLink": "https://meme-api.com/gimme"
  },
  "logoScale": 1.2,
  "iconColorType": "default",
  "wordmark": "Leave No Stone Unturned",
  "customFont": "monospaceFont",
  "fontSize": "4em",
  "fontColorType": "default",
  "fontWeight": 600,
  "maxResults": 14,
  "showbookmarkedFiles": true,
  "showRecentFiles": false,
  "maxRecentFiles": 5,
  "storeRecentFile": true,
  "showPath": true,
  "selectionHighlight": "default",
  "showShortcuts": true,
  "markdownOnly": false,
  "unresolvedLinks": true,
  "recentFilesStore": [],
  "bookmarkedFileStore": [],
  "searchDelay": 0,
  "replaceNewTabs": true,
  "newTabOnStart": true,
  "closePreviousSessionTabs": false,
  "omnisearch": false,
  "showOmnisearchExcerpt": true
}